lightfm_dataset_helper/Preprocessor.py
lightfm_dataset_helper/__init__.py
lightfm_dataset_helper/lightfm_dataset_helper.py
lightfm_dataset_helper-0.1.2.dist-info/AUTHORS.rst
lightfm_dataset_helper-0.1.2.dist-info/LICENSE
lightfm_dataset_helper-0.1.2.dist-info/METADATA
lightfm_dataset_helper-0.1.2.dist-info/WHEEL
lightfm_dataset_helper-0.1.2.dist-info/top_level.txt
lightfm_dataset_helper-0.1.2.dist-info/RECORD
