Metadata-Version: 2.1
Name: lightfm-dataset-helper
Version: 0.1.2
Summary: A small  helper for  preparing csv files for LightFM fitting
Home-page: https://github.com/Med-ELOMARI/lightfm_dataset_helper
Author: Mohamed EL Omari
Author-email: mohamed.elomari@outlook.com
License: MIT license
Keywords: lightfm_dataset_helper
Platform: UNKNOWN
Classifier: Development Status :: 2 - Pre-Alpha
Classifier: Intended Audience :: Developers
Classifier: License :: OSI Approved :: MIT License
Classifier: Natural Language :: English
Classifier: Programming Language :: Python :: 3
Classifier: Programming Language :: Python :: 3.5
Classifier: Programming Language :: Python :: 3.6
Classifier: Programming Language :: Python :: 3.7
Classifier: Programming Language :: Python :: 3.8
Requires-Python: >=3.5
